{"title":"Lua","properties":{"Lua.codeLens.enable":{"type":"boolean","scope":"resource","default":false,"markdownDescription":"%config.codeLens.enable%"},"Lua.completion.autoRequire":{"type":"boolean","scope":"resource","default":true,"markdownDescription":"%config.completion.autoRequire%"},"Lua.runtime.fileEncoding":{"markdownEnumDescriptions":["%config.runtime.fileEncoding.utf8%","%config.runtime.fileEncoding.ansi%","%config.runtime.fileEncoding.utf16le%","%config.runtime.fileEncoding.utf16be%"],"type":"string","enum":["utf8","ansi","utf16le","utf16be"],"scope":"resource","default":"utf8","markdownDescription":"%config.runtime.fileEncoding%"},"Lua.completion.displayContext":{"type":"integer","scope":"resource","default":0,"markdownDescription":"%config.completion.displayContext%"},"Lua.runtime.meta":{"type":"string","scope":"resource","default":"${version} ${language} ${encoding}","markdownDescription":"%config.runtime.meta%"},"Lua.completion.enable":{"type":"boolean","scope":"resource","default":true,"markdownDescription":"%config.completion.enable%"},"Lua.completion.keywordSnippet":{"markdownEnumDescriptions":["%config.completion.keywordSnippet.Disable%","%config.completion.keywordSnippet.Both%","%config.completion.keywordSnippet.Replace%"],"type":"string","enum":["Disable","Both","Replace"],"scope":"resource","default":"Replace","markdownDescription":"%config.completion.keywordSnippet%"},"Lua.completion.postfix":{"type":"string","scope":"resource","default":"@","markdownDescription":"%config.completion.postfix%"},"Lua.completion.requireSeparator":{"type":"string","scope":"resource","default":".","markdownDescription":"%config.completion.requireSeparator%"},"Lua.completion.showParams":{"type":"boolean","scope":"resource","default":true,"markdownDescription":"%config.completion.showParams%"},"Lua.completion.showWord":{"markdownEnumDescriptions":["%config.completion.showWord.Enable%","%config.completion.showWord.Fallback%","%config.completion.showWord.Disable%"],"type":"string","enum":["Enable","Fallback","Disable"],"scope":"resource","default":"Fallback","markdownDescription":"%config.completion.showWord%"},"Lua.diagnostics.enable":{"type":"boolean","scope":"resource","default":true,"markdownDescription":"%config.diagnostics.enable%"},"Lua.diagnostics.globals":{"type":"array","items":{"type":"string"},"scope":"resource","default":[],"markdownDescription":"%config.diagnostics.globals%"},"Lua.runtime.path":{"type":"array","items":{"type":"string"},"scope":"resource","default":["?.lua","?\/init.lua"],"markdownDescription":"%config.runtime.path%"},"Lua.completion.workspaceWord":{"type":"boolean","scope":"resource","default":true,"markdownDescription":"%config.completion.workspaceWord%"},"Lua.diagnostics.disable":{"type":"array","items":{"type":"string","enum":["action-after-return","ambiguity-1","ambiguous-syntax","args-after-dots","assign-type-mismatch","await-in-sync","block-after-else","break-outside","cast-local-type","cast-type-mismatch","circle-doc-class","close-non-object","code-after-break","codestyle-check","count-down-loop","deprecated","different-requires","discard-returns","doc-field-no-class","duplicate-doc-alias","duplicate-doc-field","duplicate-doc-param","duplicate-index","duplicate-set-field","empty-block","err-assign-as-eq","err-c-long-comment","err-comment-prefix","err-do-as-then","err-eq-as-assign","err-esc","err-nonstandard-symbol","err-then-as-do","exp-in-action","global-element","global-in-nil-env","incomplete-signature-doc","index-in-func-name","inject-field","invisible","jump-local-scope","keyword","local-limit","lowercase-global","lua-doc-miss-sign","luadoc-error-diag-mode","luadoc-miss-alias-extends","luadoc-miss-alias-name","luadoc-miss-arg-name","luadoc-miss-cate-name","luadoc-miss-class-extends-name","luadoc-miss-class-name","luadoc-miss-diag-mode","luadoc-miss-diag-name","luadoc-miss-field-extends","luadoc-miss-field-name","luadoc-miss-fun-after-overload","luadoc-miss-generic-name","luadoc-miss-local-name","luadoc-miss-module-name","luadoc-miss-operator-name","luadoc-miss-param-extends","luadoc-miss-param-name","luadoc-miss-see-name","luadoc-miss-sign-name","luadoc-miss-symbol","luadoc-miss-type-name","luadoc-miss-vararg-type","luadoc-miss-version","malformed-number","miss-end","miss-esc-x","miss-exp","miss-exponent","miss-field","miss-loop-max","miss-loop-min","miss-method","miss-name","miss-sep-in-table","miss-space-between","miss-symbol","missing-fields","missing-global-doc","missing-local-export-doc","missing-parameter","missing-return","missing-return-value","name-style-check","need-check-nil","need-paren","nesting-long-mark","newfield-call","newline-call","no-unknown","no-visible-label","not-yieldable","param-type-mismatch","redefined-label","redefined-local","redundant-parameter","redundant-return","redundant-return-value","redundant-value","return-type-mismatch","set-const","spell-check","trailing-space","unbalanced-assignments","undefined-doc-class","undefined-doc-name","undefined-doc-param","undefined-env-child","undefined-field","undefined-global","unexpect-dots","unexpect-efunc-name","unexpect-lfunc-name","unexpect-symbol","unicode-name","unknown-attribute","unknown-cast-variable","unknown-diag-code","unknown-operator","unknown-symbol","unreachable-code","unsupport-symbol","unused-function","unused-label","unused-local","unused-vararg"]},"scope":"resource","default":[],"markdownDescription":"%config.diagnostics.disable%"},"Lua.runtime.pathStrict":{"type":"boolean","scope":"resource","default":false,"markdownDescription":"%config.runtime.pathStrict%"},"Lua.diagnostics.severity":{"title":"severity","additionalProperties":false,"type":"object","scope":"resource","properties":{"invisible":{"description":"%config.diagnostics.invisible%","type":"string","enum":["Error","Warning","Information","Hint","Error!","Warning!","Information!","Hint!"],"default":"Warning"},"spell-check":{"description":"%config.diagnostics.spell-check%","type":"string","enum":["Error","Warning","Information","Hint","Error!","Warning!","Information!","Hint!"],"default":"Information"},"lowercase-global":{"description":"%config.diagnostics.lowercase-global%","type":"string","enum":["Error","Warning","Information","Hint","Error!","Warning!","Information!","Hint!"],"default":"Information"},"unbalanced-assignments":{"description":"%config.diagnostics.unbalanced-assignments%","type":"string","enum":["Error","Warning","Information","Hint","Error!","Warning!","Information!","Hint!"],"default":"Warning"},"undefined-doc-class":{"description":"%config.diagnostics.undefined-doc-class%","type":"string","enum":["Error","Warning","Information","Hint","Error!","Warning!","Information!","Hint!"],"default":"Warning"},"undefined-doc-name":{"description":"%config.diagnostics.undefined-doc-name%","type":"string","enum":["Error","Warning","Information","Hint","Error!","Warning!","Information!","Hint!"],"default":"Warning"},"undefined-doc-param":{"description":"%config.diagnostics.undefined-doc-param%","type":"string","enum":["Error","Warning","Information","Hint","Error!","Warning!","Information!","Hint!"],"default":"Warning"},"undefined-env-child":{"description":"%config.diagnostics.undefined-env-child%","type":"string","enum":["Error","Warning","Information","Hint","Error!","Warning!","Information!","Hint!"],"default":"Information"},"undefined-field":{"description":"%config.diagnostics.undefined-field%","type":"string","enum":["Error","Warning","Information","Hint","Error!","Warning!","Information!","Hint!"],"default":"Warning"},"undefined-global":{"description":"%config.diagnostics.undefined-global%","type":"string","enum":["Error","Warning","Information","Hint","Error!","Warning!","Information!","Hint!"],"default":"Warning"},"deprecated":{"description":"%config.diagnostics.deprecated%","type":"string","enum":["Error","Warning","Information","Hint","Error!","Warning!","Information!","Hint!"],"default":"Warning"},"redundant-parameter":{"description":"%config.diagnostics.redundant-parameter%","type":"string","enum":["Error","Warning","Information","Hint","Error!","Warning!","Information!","Hint!"],"default":"Warning"},"redundant-return":{"description":"%config.diagnostics.redundant-return%","type":"string","enum":["Error","Warning","Information","Hint","Error!","Warning!","Information!","Hint!"],"default":"Hint"},"missing-return":{"description":"%config.diagnostics.missing-return%","type":"string","enum":["Error","Warning","Information","Hint","Error!","Warning!","Information!","Hint!"],"default":"Warning"},"redundant-value":{"description":"%config.diagnostics.redundant-value%","type":"string","enum":["Error","Warning","Information","Hint","Error!","Warning!","Information!","Hint!"],"default":"Warning"},"unknown-cast-variable":{"description":"%config.diagnostics.unknown-cast-variable%","type":"string","enum":["Error","Warning","Information","Hint","Error!","Warning!","Information!","Hint!"],"default":"Warning"},"unknown-diag-code":{"description":"%config.diagnostics.unknown-diag-code%","type":"string","enum":["Error","Warning","Information","Hint","Error!","Warning!","Information!","Hint!"],"default":"Warning"},"unknown-operator":{"description":"%config.diagnostics.unknown-operator%","type":"string","enum":["Error","Warning","Information","Hint","Error!","Warning!","Information!","Hint!"],"default":"Warning"},"trailing-space":{"description":"%config.diagnostics.trailing-space%","type":"string","enum":["Error","Warning","Information","Hint","Error!","Warning!","Information!","Hint!"],"default":"Hint"},"unreachable-code":{"description":"%config.diagnostics.unreachable-code%","type":"string","enum":["Error","Warning","Information","Hint","Error!","Warning!","Information!","Hint!"],"default":"Hint"},"return-type-mismatch":{"description":"%config.diagnostics.return-type-mismatch%","type":"string","enum":["Error","Warning","Information","Hint","Error!","Warning!","Information!","Hint!"],"default":"Warning"},"unused-function":{"description":"%config.diagnostics.unused-function%","type":"string","enum":["Error","Warning","Information","Hint","Error!","Warning!","Information!","Hint!"],"default":"Hint"},"unused-label":{"description":"%config.diagnostics.unused-label%","type":"string","enum":["Error","Warning","Information","Hint","Error!","Warning!","Information!","Hint!"],"default":"Hint"},"unused-local":{"description":"%config.diagnostics.unused-local%","type":"string","enum":["Error","Warning","Information","Hint","Error!","Warning!","Information!","Hint!"],"default":"Hint"},"unused-vararg":{"description":"%config.diagnostics.unused-vararg%","type":"string","enum":["Error","Warning","Information","Hint","Error!","Warning!","Information!","Hint!"],"default":"Hint"},"redefined-local":{"description":"%config.diagnostics.redefined-local%","type":"string","enum":["Error","Warning","Information","Hint","Error!","Warning!","Information!","Hint!"],"default":"Hint"},"await-in-sync":{"description":"%config.diagnostics.await-in-sync%","type":"string","enum":["Error","Warning","Information","Hint","Error!","Warning!","Information!","Hint!"],"default":"Warning"},"discard-returns":{"description":"%config.diagnostics.discard-returns%","type":"string","enum":["Error","Warning","Information","Hint","Error!","Warning!","Information!","Hint!"],"default":"Warning"},"missing-global-doc":{"description":"%config.diagnostics.missing-global-doc%","type":"string","enum":["Error","Warning","Information","Hint","Error!","Warning!","Information!","Hint!"],"default":"Warning"},"missing-local-export-doc":{"description":"%config.diagnostics.missing-local-export-doc%","type":"string","enum":["Error","Warning","Information","Hint","Error!","Warning!","Information!","Hint!"],"default":"Warning"},"missing-parameter":{"description":"%config.diagnostics.missing-parameter%","type":"string","enum":["Error","Warning","Information","Hint","Error!","Warning!","Information!","Hint!"],"default":"Warning"},"need-check-nil":{"description":"%config.diagnostics.need-check-nil%","type":"string","enum":["Error","Warning","Information","Hint","Error!","Warning!","Information!","Hint!"],"default":"Warning"},"cast-local-type":{"description":"%config.diagnostics.cast-local-type%","type":"string","enum":["Error","Warning","Information","Hint","Error!","Warning!","Information!","Hint!"],"default":"Warning"},"cast-type-mismatch":{"description":"%config.diagnostics.cast-type-mismatch%","type":"string","enum":["Error","Warning","Information","Hint","Error!","Warning!","Information!","Hint!"],"default":"Warning"},"circle-doc-class":{"description":"%config.diagnostics.circle-doc-class%","type":"string","enum":["Error","Warning","Information","Hint","Error!","Warning!","Information!","Hint!"],"default":"Warning"},"close-non-object":{"description":"%config.diagnostics.close-non-object%","type":"string","enum":["Error","Warning","Information","Hint","Error!","Warning!","Information!","Hint!"],"default":"Warning"},"code-after-break":{"description":"%config.diagnostics.code-after-break%","type":"string","enum":["Error","Warning","Information","Hint","Error!","Warning!","Information!","Hint!"],"default":"Hint"},"ambiguity-1":{"description":"%config.diagnostics.ambiguity-1%","type":"string","enum":["Error","Warning","Information","Hint","Error!","Warning!","Information!","Hint!"],"default":"Warning"},"count-down-loop":{"description":"%config.diagnostics.count-down-loop%","type":"string","enum":["Error","Warning","Information","Hint","Error!","Warning!","Information!","Hint!"],"default":"Warning"},"different-requires":{"description":"%config.diagnostics.different-requires%","type":"string","enum":["Error","Warning","Information","Hint","Error!","Warning!","Information!","Hint!"],"default":"Warning"},"assign-type-mismatch":{"description":"%config.diagnostics.assign-type-mismatch%","type":"string","enum":["Error","Warning","Information","Hint","Error!","Warning!","Information!","Hint!"],"default":"Warning"},"doc-field-no-class":{"description":"%config.diagnostics.doc-field-no-class%","type":"string","enum":["Error","Warning","Information","Hint","Error!","Warning!","Information!","Hint!"],"default":"Warning"},"duplicate-doc-alias":{"description":"%config.diagnostics.duplicate-doc-alias%","type":"string","enum":["Error","Warning","Information","Hint","Error!","Warning!","Information!","Hint!"],"default":"Warning"},"duplicate-doc-field":{"description":"%config.diagnostics.duplicate-doc-field%","type":"string","enum":["Error","Warning","Information","Hint","Error!","Warning!","Information!","Hint!"],"default":"Warning"},"duplicate-doc-param":{"description":"%config.diagnostics.duplicate-doc-param%","type":"string","enum":["Error","Warning","Information","Hint","Error!","Warning!","Information!","Hint!"],"default":"Warning"},"missing-return-value":{"description":"%config.diagnostics.missing-return-value%","type":"string","enum":["Error","Warning","Information","Hint","Error!","Warning!","Information!","Hint!"],"default":"Warning"},"duplicate-set-field":{"description":"%config.diagnostics.duplicate-set-field%","type":"string","enum":["Error","Warning","Information","Hint","Error!","Warning!","Information!","Hint!"],"default":"Warning"},"empty-block":{"description":"%config.diagnostics.empty-block%","type":"string","enum":["Error","Warning","Information","Hint","Error!","Warning!","Information!","Hint!"],"default":"Hint"},"name-style-check":{"description":"%config.diagnostics.name-style-check%","type":"string","enum":["Error","Warning","Information","Hint","Error!","Warning!","Information!","Hint!"],"default":"Warning"},"duplicate-index":{"description":"%config.diagnostics.duplicate-index%","type":"string","enum":["Error","Warning","Information","Hint","Error!","Warning!","Information!","Hint!"],"default":"Warning"},"newfield-call":{"description":"%config.diagnostics.newfield-call%","type":"string","enum":["Error","Warning","Information","Hint","Error!","Warning!","Information!","Hint!"],"default":"Warning"},"newline-call":{"description":"%config.diagnostics.newline-call%","type":"string","enum":["Error","Warning","Information","Hint","Error!","Warning!","Information!","Hint!"],"default":"Warning"},"no-unknown":{"description":"%config.diagnostics.no-unknown%","type":"string","enum":["Error","Warning","Information","Hint","Error!","Warning!","Information!","Hint!"],"default":"Warning"},"codestyle-check":{"description":"%config.diagnostics.codestyle-check%","type":"string","enum":["Error","Warning","Information","Hint","Error!","Warning!","Information!","Hint!"],"default":"Warning"},"not-yieldable":{"description":"%config.diagnostics.not-yieldable%","type":"string","enum":["Error","Warning","Information","Hint","Error!","Warning!","Information!","Hint!"],"default":"Warning"},"param-type-mismatch":{"description":"%config.diagnostics.param-type-mismatch%","type":"string","enum":["Error","Warning","Information","Hint","Error!","Warning!","Information!","Hint!"],"default":"Warning"},"missing-fields":{"description":"%config.diagnostics.missing-fields%","type":"string","enum":["Error","Warning","Information","Hint","Error!","Warning!","Information!","Hint!"],"default":"Warning"},"global-element":{"description":"%config.diagnostics.global-element%","type":"string","enum":["Error","Warning","Information","Hint","Error!","Warning!","Information!","Hint!"],"default":"Warning"},"global-in-nil-env":{"description":"%config.diagnostics.global-in-nil-env%","type":"string","enum":["Error","Warning","Information","Hint","Error!","Warning!","Information!","Hint!"],"default":"Warning"},"incomplete-signature-doc":{"description":"%config.diagnostics.incomplete-signature-doc%","type":"string","enum":["Error","Warning","Information","Hint","Error!","Warning!","Information!","Hint!"],"default":"Warning"},"redundant-return-value":{"description":"%config.diagnostics.redundant-return-value%","type":"string","enum":["Error","Warning","Information","Hint","Error!","Warning!","Information!","Hint!"],"default":"Warning"},"inject-field":{"description":"%config.diagnostics.inject-field%","type":"string","enum":["Error","Warning","Information","Hint","Error!","Warning!","Information!","Hint!"],"default":"Warning"}},"markdownDescription":"%config.diagnostics.severity%"},"Lua.runtime.pluginArgs":{"type":"array","items":{"type":"string"},"scope":"resource","default":[],"markdownDescription":"%config.runtime.pluginArgs%"},"Lua.runtime.special":{"title":"special","type":"object","patternProperties":{".*":{"type":"string","default":"require","enum":["_G","rawset","rawget","setmetatable","require","dofile","loadfile","pcall","xpcall","assert","error","type","os.exit"]}},"default":{},"scope":"resource","additionalProperties":false,"markdownDescription":"%config.runtime.special%"},"Lua.diagnostics.unusedLocalExclude":{"type":"array","items":{"type":"string"},"scope":"resource","default":[],"markdownDescription":"%config.diagnostics.unusedLocalExclude%"},"Lua.runtime.unicodeName":{"type":"boolean","scope":"resource","default":false,"markdownDescription":"%config.runtime.unicodeName%"},"Lua.diagnostics.workspaceDelay":{"type":"integer","scope":"resource","default":3000,"markdownDescription":"%config.diagnostics.workspaceDelay%"},"Lua.runtime.version":{"markdownEnumDescriptions":["%config.runtime.version.Lua 5.1%","%config.runtime.version.Lua 5.2%","%config.runtime.version.Lua 5.3%","%config.runtime.version.Lua 5.4%","%config.runtime.version.LuaJIT%"],"type":"string","enum":["Lua 5.1","Lua 5.2","Lua 5.3","Lua 5.4","LuaJIT"],"scope":"resource","default":"Lua 5.4","markdownDescription":"%config.runtime.version%"},"Lua.diagnostics.workspaceEvent":{"markdownEnumDescriptions":["%config.diagnostics.workspaceEvent.OnChange%","%config.diagnostics.workspaceEvent.OnSave%","%config.diagnostics.workspaceEvent.None%"],"type":"string","enum":["OnChange","OnSave","None"],"scope":"resource","default":"OnSave","markdownDescription":"%config.diagnostics.workspaceEvent%"},"Lua.diagnostics.workspaceRate":{"type":"integer","scope":"resource","default":100,"markdownDescription":"%config.diagnostics.workspaceRate%"},"Lua.semantic.annotation":{"type":"boolean","scope":"resource","default":true,"markdownDescription":"%config.semantic.annotation%"},"Lua.semantic.enable":{"type":"boolean","scope":"resource","default":true,"markdownDescription":"%config.semantic.enable%"},"Lua.diagnostics.groupSeverity":{"title":"groupSeverity","additionalProperties":false,"type":"object","scope":"resource","properties":{"redefined":{"description":"%config.diagnostics.redefined%","type":"string","enum":["Error","Warning","Information","Hint","Fallback"],"default":"Fallback"},"strict":{"description":"%config.diagnostics.strict%","type":"string","enum":["Error","Warning","Information","Hint","Fallback"],"default":"Fallback"},"ambiguity":{"description":"%config.diagnostics.ambiguity%","type":"string","enum":["Error","Warning","Information","Hint","Fallback"],"default":"Fallback"},"strong":{"description":"%config.diagnostics.strong%","type":"string","enum":["Error","Warning","Information","Hint","Fallback"],"default":"Fallback"},"type-check":{"description":"%config.diagnostics.type-check%","type":"string","enum":["Error","Warning","Information","Hint","Fallback"],"default":"Fallback"},"luadoc":{"description":"%config.diagnostics.luadoc%","type":"string","enum":["Error","Warning","Information","Hint","Fallback"],"default":"Fallback"},"unbalanced":{"description":"%config.diagnostics.unbalanced%","type":"string","enum":["Error","Warning","Information","Hint","Fallback"],"default":"Fallback"},"await":{"description":"%config.diagnostics.await%","type":"string","enum":["Error","Warning","Information","Hint","Fallback"],"default":"Fallback"},"unused":{"description":"%config.diagnostics.unused%","type":"string","enum":["Error","Warning","Information","Hint","Fallback"],"default":"Fallback"},"conventions":{"description":"%config.diagnostics.conventions%","type":"string","enum":["Error","Warning","Information","Hint","Fallback"],"default":"Fallback"},"global":{"description":"%config.diagnostics.global%","type":"string","enum":["Error","Warning","Information","Hint","Fallback"],"default":"Fallback"},"duplicate":{"description":"%config.diagnostics.duplicate%","type":"string","enum":["Error","Warning","Information","Hint","Fallback"],"default":"Fallback"},"codestyle":{"description":"%config.diagnostics.codestyle%","type":"string","enum":["Error","Warning","Information","Hint","Fallback"],"default":"Fallback"}},"markdownDescription":"%config.diagnostics.groupSeverity%"},"Lua.semantic.keyword":{"type":"boolean","scope":"resource","default":false,"markdownDescription":"%config.semantic.keyword%"},"Lua.semantic.variable":{"type":"boolean","scope":"resource","default":true,"markdownDescription":"%config.semantic.variable%"},"Lua.signatureHelp.enable":{"type":"boolean","scope":"resource","default":true,"markdownDescription":"%config.signatureHelp.enable%"},"Lua.format.enable":{"type":"boolean","scope":"resource","default":true,"markdownDescription":"%config.format.enable%"},"Lua.diagnostics.libraryFiles":{"markdownEnumDescriptions":["%config.diagnostics.libraryFiles.Enable%","%config.diagnostics.libraryFiles.Opened%","%config.diagnostics.libraryFiles.Disable%"],"type":"string","enum":["Enable","Opened","Disable"],"scope":"resource","default":"Opened","markdownDescription":"%config.diagnostics.libraryFiles%"},"Lua.hint.arrayIndex":{"markdownEnumDescriptions":["%config.hint.arrayIndex.Enable%","%config.hint.arrayIndex.Auto%","%config.hint.arrayIndex.Disable%"],"type":"string","enum":["Enable","Auto","Disable"],"scope":"resource","default":"Auto","markdownDescription":"%config.hint.arrayIndex%"},"Lua.type.weakNilCheck":{"type":"boolean","scope":"resource","default":false,"markdownDescription":"%config.type.weakNilCheck%"},"Lua.diagnostics.neededFileStatus":{"title":"neededFileStatus","additionalProperties":false,"type":"object","scope":"resource","properties":{"invisible":{"description":"%config.diagnostics.invisible%","type":"string","enum":["Any","Opened","None","Any!","Opened!","None!"],"default":"Any"},"spell-check":{"description":"%config.diagnostics.spell-check%","type":"string","enum":["Any","Opened","None","Any!","Opened!","None!"],"default":"None"},"lowercase-global":{"description":"%config.diagnostics.lowercase-global%","type":"string","enum":["Any","Opened","None","Any!","Opened!","None!"],"default":"Any"},"unbalanced-assignments":{"description":"%config.diagnostics.unbalanced-assignments%","type":"string","enum":["Any","Opened","None","Any!","Opened!","None!"],"default":"Any"},"undefined-doc-class":{"description":"%config.diagnostics.undefined-doc-class%","type":"string","enum":["Any","Opened","None","Any!","Opened!","None!"],"default":"Any"},"undefined-doc-name":{"description":"%config.diagnostics.undefined-doc-name%","type":"string","enum":["Any","Opened","None","Any!","Opened!","None!"],"default":"Any"},"undefined-doc-param":{"description":"%config.diagnostics.undefined-doc-param%","type":"string","enum":["Any","Opened","None","Any!","Opened!","None!"],"default":"Any"},"undefined-env-child":{"description":"%config.diagnostics.undefined-env-child%","type":"string","enum":["Any","Opened","None","Any!","Opened!","None!"],"default":"Any"},"undefined-field":{"description":"%config.diagnostics.undefined-field%","type":"string","enum":["Any","Opened","None","Any!","Opened!","None!"],"default":"Opened"},"undefined-global":{"description":"%config.diagnostics.undefined-global%","type":"string","enum":["Any","Opened","None","Any!","Opened!","None!"],"default":"Any"},"deprecated":{"description":"%config.diagnostics.deprecated%","type":"string","enum":["Any","Opened","None","Any!","Opened!","None!"],"default":"Any"},"redundant-parameter":{"description":"%config.diagnostics.redundant-parameter%","type":"string","enum":["Any","Opened","None","Any!","Opened!","None!"],"default":"Any"},"redundant-return":{"description":"%config.diagnostics.redundant-return%","type":"string","enum":["Any","Opened","None","Any!","Opened!","None!"],"default":"Opened"},"missing-return":{"description":"%config.diagnostics.missing-return%","type":"string","enum":["Any","Opened","None","Any!","Opened!","None!"],"default":"Any"},"redundant-value":{"description":"%config.diagnostics.redundant-value%","type":"string","enum":["Any","Opened","None","Any!","Opened!","None!"],"default":"Any"},"unknown-cast-variable":{"description":"%config.diagnostics.unknown-cast-variable%","type":"string","enum":["Any","Opened","None","Any!","Opened!","None!"],"default":"Any"},"unknown-diag-code":{"description":"%config.diagnostics.unknown-diag-code%","type":"string","enum":["Any","Opened","None","Any!","Opened!","None!"],"default":"Any"},"unknown-operator":{"description":"%config.diagnostics.unknown-operator%","type":"string","enum":["Any","Opened","None","Any!","Opened!","None!"],"default":"Any"},"trailing-space":{"description":"%config.diagnostics.trailing-space%","type":"string","enum":["Any","Opened","None","Any!","Opened!","None!"],"default":"Opened"},"unreachable-code":{"description":"%config.diagnostics.unreachable-code%","type":"string","enum":["Any","Opened","None","Any!","Opened!","None!"],"default":"Opened"},"return-type-mismatch":{"description":"%config.diagnostics.return-type-mismatch%","type":"string","enum":["Any","Opened","None","Any!","Opened!","None!"],"default":"Opened"},"unused-function":{"description":"%config.diagnostics.unused-function%","type":"string","enum":["Any","Opened","None","Any!","Opened!","None!"],"default":"Opened"},"unused-label":{"description":"%config.diagnostics.unused-label%","type":"string","enum":["Any","Opened","None","Any!","Opened!","None!"],"default":"Opened"},"unused-local":{"description":"%config.diagnostics.unused-local%","type":"string","enum":["Any","Opened","None","Any!","Opened!","None!"],"default":"Opened"},"unused-vararg":{"description":"%config.diagnostics.unused-vararg%","type":"string","enum":["Any","Opened","None","Any!","Opened!","None!"],"default":"Opened"},"redefined-local":{"description":"%config.diagnostics.redefined-local%","type":"string","enum":["Any","Opened","None","Any!","Opened!","None!"],"default":"Opened"},"await-in-sync":{"description":"%config.diagnostics.await-in-sync%","type":"string","enum":["Any","Opened","None","Any!","Opened!","None!"],"default":"None"},"discard-returns":{"description":"%config.diagnostics.discard-returns%","type":"string","enum":["Any","Opened","None","Any!","Opened!","None!"],"default":"Any"},"missing-global-doc":{"description":"%config.diagnostics.missing-global-doc%","type":"string","enum":["Any","Opened","None","Any!","Opened!","None!"],"default":"None"},"missing-local-export-doc":{"description":"%config.diagnostics.missing-local-export-doc%","type":"string","enum":["Any","Opened","None","Any!","Opened!","None!"],"default":"None"},"missing-parameter":{"description":"%config.diagnostics.missing-parameter%","type":"string","enum":["Any","Opened","None","Any!","Opened!","None!"],"default":"Any"},"need-check-nil":{"description":"%config.diagnostics.need-check-nil%","type":"string","enum":["Any","Opened","None","Any!","Opened!","None!"],"default":"Opened"},"cast-local-type":{"description":"%config.diagnostics.cast-local-type%","type":"string","enum":["Any","Opened","None","Any!","Opened!","None!"],"default":"Opened"},"cast-type-mismatch":{"description":"%config.diagnostics.cast-type-mismatch%","type":"string","enum":["Any","Opened","None","Any!","Opened!","None!"],"default":"Opened"},"circle-doc-class":{"description":"%config.diagnostics.circle-doc-class%","type":"string","enum":["Any","Opened","None","Any!","Opened!","None!"],"default":"Any"},"close-non-object":{"description":"%config.diagnostics.close-non-object%","type":"string","enum":["Any","Opened","None","Any!","Opened!","None!"],"default":"Any"},"code-after-break":{"description":"%config.diagnostics.code-after-break%","type":"string","enum":["Any","Opened","None","Any!","Opened!","None!"],"default":"Opened"},"ambiguity-1":{"description":"%config.diagnostics.ambiguity-1%","type":"string","enum":["Any","Opened","None","Any!","Opened!","None!"],"default":"Any"},"count-down-loop":{"description":"%config.diagnostics.count-down-loop%","type":"string","enum":["Any","Opened","None","Any!","Opened!","None!"],"default":"Any"},"different-requires":{"description":"%config.diagnostics.different-requires%","type":"string","enum":["Any","Opened","None","Any!","Opened!","None!"],"default":"Any"},"assign-type-mismatch":{"description":"%config.diagnostics.assign-type-mismatch%","type":"string","enum":["Any","Opened","None","Any!","Opened!","None!"],"default":"Opened"},"doc-field-no-class":{"description":"%config.diagnostics.doc-field-no-class%","type":"string","enum":["Any","Opened","None","Any!","Opened!","None!"],"default":"Any"},"duplicate-doc-alias":{"description":"%config.diagnostics.duplicate-doc-alias%","type":"string","enum":["Any","Opened","None","Any!","Opened!","None!"],"default":"Any"},"duplicate-doc-field":{"description":"%config.diagnostics.duplicate-doc-field%","type":"string","enum":["Any","Opened","None","Any!","Opened!","None!"],"default":"Any"},"duplicate-doc-param":{"description":"%config.diagnostics.duplicate-doc-param%","type":"string","enum":["Any","Opened","None","Any!","Opened!","None!"],"default":"Any"},"missing-return-value":{"description":"%config.diagnostics.missing-return-value%","type":"string","enum":["Any","Opened","None","Any!","Opened!","None!"],"default":"Any"},"duplicate-set-field":{"description":"%config.diagnostics.duplicate-set-field%","type":"string","enum":["Any","Opened","None","Any!","Opened!","None!"],"default":"Opened"},"empty-block":{"description":"%config.diagnostics.empty-block%","type":"string","enum":["Any","Opened","None","Any!","Opened!","None!"],"default":"Opened"},"name-style-check":{"description":"%config.diagnostics.name-style-check%","type":"string","enum":["Any","Opened","None","Any!","Opened!","None!"],"default":"None"},"duplicate-index":{"description":"%config.diagnostics.duplicate-index%","type":"string","enum":["Any","Opened","None","Any!","Opened!","None!"],"default":"Any"},"newfield-call":{"description":"%config.diagnostics.newfield-call%","type":"string","enum":["Any","Opened","None","Any!","Opened!","None!"],"default":"Any"},"newline-call":{"description":"%config.diagnostics.newline-call%","type":"string","enum":["Any","Opened","None","Any!","Opened!","None!"],"default":"Any"},"no-unknown":{"description":"%config.diagnostics.no-unknown%","type":"string","enum":["Any","Opened","None","Any!","Opened!","None!"],"default":"None"},"codestyle-check":{"description":"%config.diagnostics.codestyle-check%","type":"string","enum":["Any","Opened","None","Any!","Opened!","None!"],"default":"None"},"not-yieldable":{"description":"%config.diagnostics.not-yieldable%","type":"string","enum":["Any","Opened","None","Any!","Opened!","None!"],"default":"None"},"param-type-mismatch":{"description":"%config.diagnostics.param-type-mismatch%","type":"string","enum":["Any","Opened","None","Any!","Opened!","None!"],"default":"Opened"},"missing-fields":{"description":"%config.diagnostics.missing-fields%","type":"string","enum":["Any","Opened","None","Any!","Opened!","None!"],"default":"Any"},"global-element":{"description":"%config.diagnostics.global-element%","type":"string","enum":["Any","Opened","None","Any!","Opened!","None!"],"default":"None"},"global-in-nil-env":{"description":"%config.diagnostics.global-in-nil-env%","type":"string","enum":["Any","Opened","None","Any!","Opened!","None!"],"default":"Any"},"incomplete-signature-doc":{"description":"%config.diagnostics.incomplete-signature-doc%","type":"string","enum":["Any","Opened","None","Any!","Opened!","None!"],"default":"None"},"redundant-return-value":{"description":"%config.diagnostics.redundant-return-value%","type":"string","enum":["Any","Opened","None","Any!","Opened!","None!"],"default":"Any"},"inject-field":{"description":"%config.diagnostics.inject-field%","type":"string","enum":["Any","Opened","None","Any!","Opened!","None!"],"default":"Opened"}},"markdownDescription":"%config.diagnostics.neededFileStatus%"},"Lua.hint.await":{"type":"boolean","scope":"resource","default":true,"markdownDescription":"%config.hint.await%"},"Lua.typeFormat.config":{"title":"config","additionalProperties":false,"type":"object","scope":"resource","properties":{"auto_complete_table_sep":{"description":"%config.typeFormat.config.auto_complete_table_sep%","type":"string","default":"true"},"format_line":{"description":"%config.typeFormat.config.format_line%","type":"string","default":"true"},"auto_complete_end":{"description":"%config.typeFormat.config.auto_complete_end%","type":"string","default":"true"}},"markdownDescription":"%config.typeFormat.config%"},"Lua.hint.enable":{"type":"boolean","scope":"resource","default":false,"markdownDescription":"%config.hint.enable%"},"Lua.hint.paramName":{"markdownEnumDescriptions":["%config.hint.paramName.All%","%config.hint.paramName.Literal%","%config.hint.paramName.Disable%"],"type":"string","enum":["All","Literal","Disable"],"scope":"resource","default":"All","markdownDescription":"%config.hint.paramName%"},"Lua.window.progressBar":{"type":"boolean","scope":"resource","default":true,"markdownDescription":"%config.window.progressBar%"},"Lua.hint.paramType":{"type":"boolean","scope":"resource","default":true,"markdownDescription":"%config.hint.paramType%"},"Lua.window.statusBar":{"type":"boolean","scope":"resource","default":true,"markdownDescription":"%config.window.statusBar%"},"Lua.hint.semicolon":{"markdownEnumDescriptions":["%config.hint.semicolon.All%","%config.hint.semicolon.SameLine%","%config.hint.semicolon.Disable%"],"type":"string","enum":["All","SameLine","Disable"],"scope":"resource","default":"SameLine","markdownDescription":"%config.hint.semicolon%"},"Lua.workspace.checkThirdParty":{"scope":"resource","type":["string","boolean"],"markdownDescription":"%config.workspace.checkThirdParty%"},"Lua.workspace.ignoreDir":{"type":"array","items":{"type":"string"},"scope":"resource","default":[".vscode"],"markdownDescription":"%config.workspace.ignoreDir%"},"Lua.hint.setType":{"type":"boolean","scope":"resource","default":false,"markdownDescription":"%config.hint.setType%"},"Lua.hover.enable":{"type":"boolean","scope":"resource","default":true,"markdownDescription":"%config.hover.enable%"},"Lua.hover.enumsLimit":{"type":"integer","scope":"resource","default":5,"markdownDescription":"%config.hover.enumsLimit%"},"Lua.workspace.userThirdParty":{"type":"array","items":{"type":"string"},"scope":"resource","default":[],"markdownDescription":"%config.workspace.userThirdParty%"},"Lua.hover.expandAlias":{"type":"boolean","scope":"resource","default":true,"markdownDescription":"%config.hover.expandAlias%"},"Lua.workspace.useGitIgnore":{"type":"boolean","scope":"resource","default":true,"markdownDescription":"%config.workspace.useGitIgnore%"},"Lua.hover.previewFields":{"type":"integer","scope":"resource","default":50,"markdownDescription":"%config.hover.previewFields%"},"Lua.workspace.preloadFileSize":{"type":"integer","scope":"resource","default":500,"markdownDescription":"%config.workspace.preloadFileSize%"},"Lua.hover.viewNumber":{"type":"boolean","scope":"resource","default":true,"markdownDescription":"%config.hover.viewNumber%"},"Lua.workspace.maxPreload":{"type":"integer","scope":"resource","default":5000,"markdownDescription":"%config.workspace.maxPreload%"},"Lua.hover.viewString":{"type":"boolean","scope":"resource","default":true,"markdownDescription":"%config.hover.viewString%"},"Lua.workspace.library":{"type":"array","items":{"type":"string"},"scope":"resource","default":[],"markdownDescription":"%config.workspace.library%"},"Lua.hover.viewStringMax":{"type":"integer","scope":"resource","default":1000,"markdownDescription":"%config.hover.viewStringMax%"},"Lua.workspace.ignoreSubmodules":{"type":"boolean","scope":"resource","default":true,"markdownDescription":"%config.workspace.ignoreSubmodules%"},"Lua.misc.executablePath":{"type":"string","scope":"resource","default":"","markdownDescription":"%config.misc.executablePath%"},"Lua.type.weakUnionCheck":{"type":"boolean","scope":"resource","default":false,"markdownDescription":"%config.type.weakUnionCheck%"},"Lua.runtime.plugin":{"type":"string","scope":"resource","default":"","markdownDescription":"%config.runtime.plugin%"},"Lua.nameStyle.config":{"title":"config","type":"object","patternProperties":{".*":{"type":["string","array"]}},"default":{},"scope":"resource","additionalProperties":false,"markdownDescription":"%config.nameStyle.config%"},"Lua.type.castNumberToInteger":{"type":"boolean","scope":"resource","default":true,"markdownDescription":"%config.type.castNumberToInteger%"},"Lua.runtime.builtin":{"title":"builtin","additionalProperties":false,"type":"object","scope":"resource","properties":{"package":{"description":"%config.runtime.builtin.package%","type":"string","enum":["default","enable","disable"],"default":"default"},"jit.profile":{"description":"%config.runtime.builtin.jit.profile%","type":"string","enum":["default","enable","disable"],"default":"default"},"jit.util":{"description":"%config.runtime.builtin.jit.util%","type":"string","enum":["default","enable","disable"],"default":"default"},"string.buffer":{"description":"%config.runtime.builtin.string.buffer%","type":"string","enum":["default","enable","disable"],"default":"default"},"math":{"description":"%config.runtime.builtin.math%","type":"string","enum":["default","enable","disable"],"default":"default"},"ffi":{"description":"%config.runtime.builtin.ffi%","type":"string","enum":["default","enable","disable"],"default":"default"},"bit":{"description":"%config.runtime.builtin.bit%","type":"string","enum":["default","enable","disable"],"default":"default"},"builtin":{"description":"%config.runtime.builtin.builtin%","type":"string","enum":["default","enable","disable"],"default":"default"},"os":{"description":"%config.runtime.builtin.os%","type":"string","enum":["default","enable","disable"],"default":"default"},"bit32":{"description":"%config.runtime.builtin.bit32%","type":"string","enum":["default","enable","disable"],"default":"default"},"debug":{"description":"%config.runtime.builtin.debug%","type":"string","enum":["default","enable","disable"],"default":"default"},"string":{"description":"%config.runtime.builtin.string%","type":"string","enum":["default","enable","disable"],"default":"default"},"table.new":{"description":"%config.runtime.builtin.table.new%","type":"string","enum":["default","enable","disable"],"default":"default"},"utf8":{"description":"%config.runtime.builtin.utf8%","type":"string","enum":["default","enable","disable"],"default":"default"},"coroutine":{"description":"%config.runtime.builtin.coroutine%","type":"string","enum":["default","enable","disable"],"default":"default"},"jit":{"description":"%config.runtime.builtin.jit%","type":"string","enum":["default","enable","disable"],"default":"default"},"basic":{"description":"%config.runtime.builtin.basic%","type":"string","enum":["default","enable","disable"],"default":"default"},"table":{"description":"%config.runtime.builtin.table%","type":"string","enum":["default","enable","disable"],"default":"default"},"table.clear":{"description":"%config.runtime.builtin.table.clear%","type":"string","enum":["default","enable","disable"],"default":"default"},"io":{"description":"%config.runtime.builtin.io%","type":"string","enum":["default","enable","disable"],"default":"default"}},"markdownDescription":"%config.runtime.builtin%"},"Lua.spell.dict":{"type":"array","items":{"type":"string"},"scope":"resource","default":[],"markdownDescription":"%config.spell.dict%"},"Lua.doc.protectedName":{"type":"array","items":{"type":"string"},"scope":"resource","default":[],"markdownDescription":"%config.doc.protectedName%"},"Lua.diagnostics.groupFileStatus":{"title":"groupFileStatus","additionalProperties":false,"type":"object","scope":"resource","properties":{"redefined":{"description":"%config.diagnostics.redefined%","type":"string","enum":["Any","Opened","None","Fallback"],"default":"Fallback"},"strict":{"description":"%config.diagnostics.strict%","type":"string","enum":["Any","Opened","None","Fallback"],"default":"Fallback"},"ambiguity":{"description":"%config.diagnostics.ambiguity%","type":"string","enum":["Any","Opened","None","Fallback"],"default":"Fallback"},"strong":{"description":"%config.diagnostics.strong%","type":"string","enum":["Any","Opened","None","Fallback"],"default":"Fallback"},"type-check":{"description":"%config.diagnostics.type-check%","type":"string","enum":["Any","Opened","None","Fallback"],"default":"Fallback"},"luadoc":{"description":"%config.diagnostics.luadoc%","type":"string","enum":["Any","Opened","None","Fallback"],"default":"Fallback"},"unbalanced":{"description":"%config.diagnostics.unbalanced%","type":"string","enum":["Any","Opened","None","Fallback"],"default":"Fallback"},"await":{"description":"%config.diagnostics.await%","type":"string","enum":["Any","Opened","None","Fallback"],"default":"Fallback"},"unused":{"description":"%config.diagnostics.unused%","type":"string","enum":["Any","Opened","None","Fallback"],"default":"Fallback"},"conventions":{"description":"%config.diagnostics.conventions%","type":"string","enum":["Any","Opened","None","Fallback"],"default":"Fallback"},"global":{"description":"%config.diagnostics.global%","type":"string","enum":["Any","Opened","None","Fallback"],"default":"Fallback"},"duplicate":{"description":"%config.diagnostics.duplicate%","type":"string","enum":["Any","Opened","None","Fallback"],"default":"Fallback"},"codestyle":{"description":"%config.diagnostics.codestyle%","type":"string","enum":["Any","Opened","None","Fallback"],"default":"Fallback"}},"markdownDescription":"%config.diagnostics.groupFileStatus%"},"Lua.doc.privateName":{"type":"array","items":{"type":"string"},"scope":"resource","default":[],"markdownDescription":"%config.doc.privateName%"},"Lua.diagnostics.ignoredFiles":{"markdownEnumDescriptions":["%config.diagnostics.ignoredFiles.Enable%","%config.diagnostics.ignoredFiles.Opened%","%config.diagnostics.ignoredFiles.Disable%"],"type":"string","enum":["Enable","Opened","Disable"],"scope":"resource","default":"Opened","markdownDescription":"%config.diagnostics.ignoredFiles%"},"Lua.doc.packageName":{"type":"array","items":{"type":"string"},"scope":"resource","default":[],"markdownDescription":"%config.doc.packageName%"},"Lua.diagnostics.disableScheme":{"type":"array","items":{"type":"string"},"scope":"resource","default":["git"],"markdownDescription":"%config.diagnostics.disableScheme%"},"Lua.format.defaultConfig":{"title":"defaultConfig","type":"object","patternProperties":{".*":{"type":"string","default":""}},"default":{},"scope":"resource","additionalProperties":false,"markdownDescription":"%config.format.defaultConfig%"},"Lua.completion.callSnippet":{"markdownEnumDescriptions":["%config.completion.callSnippet.Disable%","%config.completion.callSnippet.Both%","%config.completion.callSnippet.Replace%"],"type":"string","enum":["Disable","Both","Replace"],"scope":"resource","default":"Disable","markdownDescription":"%config.completion.callSnippet%"},"Lua.misc.parameters":{"type":"array","items":{"type":"string"},"scope":"resource","default":[],"markdownDescription":"%config.misc.parameters%"},"Lua.addonManager.enable":{"type":"boolean","scope":"resource","default":true,"markdownDescription":"%config.addonManager.enable%"},"Lua.runtime.nonstandardSymbol":{"type":"array","items":{"type":"string","enum":["\/\/","\/**\/","`","+=","-=","*=","\/=","%=","^=","\/\/=","|=","&=","<<=",">>=","||","&&","!","!=","continue"]},"scope":"resource","default":[],"markdownDescription":"%config.runtime.nonstandardSymbol%"}},"type":"object"}